{
    "_links": {
        "self": {
            "href": "http:\/\/default\/fr\/media\/8\/edit?_format=hal_json"
        },
        "type": {
            "href": "http:\/\/drupal.org\/rest\/type\/media\/image"
        },
        "http:\/\/drupal.org\/rest\/relation\/media\/image\/uid": [
            {
                "href": "http:\/\/default\/en\/user\/1?_format=hal_json"
            }
        ],
        "http:\/\/drupal.org\/rest\/relation\/media\/image\/thumbnail": [
            {
                "href": "http:\/\/default\/fr\/file\/8?_format=hal_json"
            }
        ],
        "http:\/\/drupal.org\/rest\/relation\/media\/image\/field_media_image": [
            {
                "href": "http:\/\/default\/fr\/file\/8?_format=hal_json"
            }
        ]
    },
    "mid": [
        {
            "value": 8
        }
    ],
    "uuid": [
        {
            "value": "0c7c2631-0354-4784-957e-2d0bac2c606b"
        }
    ],
    "vid": [
        {
            "value": 8
        }
    ],
    "langcode": [
        {
            "value": "fr",
            "lang": "fr"
        }
    ],
    "bundle": [
        {
            "target_id": "image"
        }
    ],
    "revision_created": [
        {
            "value": "2020-06-17T20:34:34+00:00",
            "format": "Y-m-d\\TH:i:sP"
        }
    ],
    "status": [
        {
            "value": true
        }
    ],
    "_embedded": {
        "http:\/\/drupal.org\/rest\/relation\/media\/image\/uid": [
            {
                "_links": {
                    "self": {
                        "href": "http:\/\/default\/en\/user\/1?_format=hal_json"
                    },
                    "type": {
                        "href": "http:\/\/drupal.org\/rest\/type\/user\/user"
                    }
                },
                "uuid": [
                    {
                        "value": "d7501914-4ca1-4f93-8af1-35bef377bbb2"
                    }
                ]
            }
        ],
        "http:\/\/drupal.org\/rest\/relation\/media\/image\/thumbnail": [
            {
                "_links": {
                    "self": {
                        "href": "http:\/\/default\/fr\/file\/8?_format=hal_json"
                    },
                    "type": {
                        "href": "http:\/\/drupal.org\/rest\/type\/file\/image"
                    }
                },
                "uuid": [
                    {
                        "value": "2de4a1ec-676f-4572-96aa-8dd0db9980bc"
                    }
                ],
                "alt": "News 7",
                "title": null,
                "width": "891",
                "height": "500"
            }
        ],
        "http:\/\/drupal.org\/rest\/relation\/media\/image\/field_media_image": [
            {
                "_links": {
                    "self": {
                        "href": "http:\/\/default\/fr\/file\/8?_format=hal_json"
                    },
                    "type": {
                        "href": "http:\/\/drupal.org\/rest\/type\/file\/image"
                    }
                },
                "uuid": [
                    {
                        "value": "2de4a1ec-676f-4572-96aa-8dd0db9980bc"
                    }
                ],
                "alt": "News 7",
                "title": "",
                "width": "891",
                "height": "500"
            }
        ]
    },
    "name": [
        {
            "value": "photo-1561266311-e0e31ff8939d.jpeg"
        }
    ],
    "created": [
        {
            "value": "2020-06-17T20:34:31+00:00",
            "format": "Y-m-d\\TH:i:sP"
        }
    ],
    "changed": [
        {
            "value": "2020-06-17T20:34:31+00:00",
            "format": "Y-m-d\\TH:i:sP"
        }
    ],
    "default_langcode": [
        {
            "value": true,
            "lang": "fr"
        }
    ],
    "revision_translation_affected": [
        {
            "value": true,
            "lang": "fr"
        }
    ]
}